chinaunicomuntis/DBConn.py
chinaunicomuntis/__init__.py
chinaunicomuntis/mylogger.py
example/__init__.py
example/math.py
chinaunicom-1.0.12.dist-info/LICENSE
chinaunicom-1.0.12.dist-info/METADATA
chinaunicom-1.0.12.dist-info/WHEEL
chinaunicom-1.0.12.dist-info/top_level.txt
chinaunicom-1.0.12.dist-info/RECORD
