Metadata-Version: 2.1
Name: chinaunicom
Version: 1.0.12
Summary: 中国联通软件研究院专用python工具包
Home-page: https://github.com/JustDoPython/justdopython.github.io
Author: 王若蒙
Author-email: wangrm40@chinaunicom.cn
License: UNKNOWN
Platform: UNKNOWN
Classifier: Programming Language :: Python :: 3
Classifier: License :: OSI Approved :: MIT License
Classifier: Operating System :: OS Independent
